datasette_ml/__init__.py
datasette_ml/py.typed
datasette_ml-0.1.2.dist-info/LICENSE
datasette_ml-0.1.2.dist-info/METADATA
datasette_ml-0.1.2.dist-info/WHEEL
datasette_ml-0.1.2.dist-info/entry_points.txt
datasette_ml-0.1.2.dist-info/RECORD
