Metadata-Version: 2.1
Name: datasette-ml
Version: 0.1.2
Summary: A Datasette plugin providing an MLOps platform to train, eval and predict machine learning models
Home-page: https://github.com/rclement/datasette-ml
License: Apache License, Version 2.0
Author: Romain Clement
Requires-Python: >=3.8.1,<4.0.0
Classifier: License :: Other/Proprietary License
Classifier: Programming Language :: Python :: 3
Classifier: Programming Language :: Python :: 3.9
Classifier: Programming Language :: Python :: 3.10
Classifier: Programming Language :: Python :: 3.11
Requires-Dist: datasette
Requires-Dist: sqlite-ml (==0.1.2)
Project-URL: Repository, https://github.com/rclement/datasette-ml
